[{"pos": [-840, -960], "type": "block-Snow-3"}, {"pos": [-780, -960], "type": "block-Snow-1"}, {"pos": [-720, -960], "type": "block-Snow-1"}, {"pos": [-660, -960], "type": "block-Snow-1"}, {"pos": [-600, -960], "type": "block-Snow-1"}, {"pos": [-540, -960], "type": "block-Snow-1"}, {"pos": [-480, -960], "type": "block-Snow-1"}, {"pos": [-420, -960], "type": "block-Snow-1"}, {"pos": [-360, -960], "type": "block-Snow-1"}, {"pos": [-300, -960], "type": "block-Snow-1"}, {"pos": [-240, -960], "type": "block-Snow-1"}, {"pos": [-180, -960], "type": "block-Snow-1"}, {"pos": [-120, -960], "type": "block-Snow-1"}, {"pos": [-60, -960], "type": "block-Snow-1"}, {"pos": [0, -960], "type": "block-Snow-1"}, {"pos": [60, -960], "type": "block-Snow-1"}, {"pos": [-840, -1200], "type": "block-Snow-3"}, {"pos": [-840, -1140], "type": "block-Snow-3"}, {"pos": [-840, -1080], "type": "block-Snow-3"}, {"pos": [-840, -1020], "type": "block-Snow-3"}, {"pos": [-840, -1260], "type": "block-Snow-1"}, {"pos": [120, -960], "type": "block-Snow-1"}, {"pos": [180, -960], "type": "block-Snow-1"}, {"pos": [240, -960], "type": "block-Snow-1"}, {"pos": [300, -960], "type": "block-Snow-1"}, {"pos": [360, -960], "type": "block-Snow-1"}, {"pos": [420, -960], "type": "block-Snow-1"}, {"pos": [480, -960], "type": "block-Snow-1"}, {"pos": [540, -960], "type": "block-Snow-1"}, {"pos": [600, -960], "type": "block-Snow-1"}, {"pos": [660, -960], "type": "block-Snow-1"}, {"pos": [720, -960], "type": "block-Snow-1"}, {"pos": [780, -960], "type": "block-Snow-1"}, {"pos": [840, -960], "type": "block-Snow-1"}, {"pos": [900, -960], "type": "block-Snow-1"}, {"pos": [960, -960], "type": "block-Snow-1"}, {"pos": [1020, -960], "type": "block-Snow-2"}, {"pos": [1380, -1260], "type": "block-Snow-1"}, {"pos": [1380, -1200], "type": "block-Snow-3"}, {"pos": [1380, -1140], "type": "block-Snow-3"}, {"pos": [1380, -1080], "type": "block-Snow-3"}, {"pos": [1380, -1020], "type": "block-Snow-3"}, {"pos": [1380, -960], "type": "block-Snow-3"}, {"pos": [1380, -900], "type": "block-Snow-3"}, {"pos": [1380, -840], "type": "block-Snow-3"}, {"pos": [1380, -780], "type": "block-Snow-3"}, {"pos": [1380, -720], "type": "block-Snow-3"}, {"pos": [1200, -780], "type": "block-Snow-1"}, {"pos": [1380, -660], "type": "block-Snow-3"}, {"pos": [1380, -600], "type": "block-Snow-3"}, {"pos": [1320, -600], "type": "block-Snow-1"}, {"pos": [1260, -600], "type": "block-Snow-1"}, {"pos": [1200, -600], "type": "block-Snow-1"}, {"pos": [1140, -600], "type": "block-Snow-1"}, {"pos": [1080, -600], "type": "block-Snow-1"}, {"pos": [1020, -600], "type": "block-Snow-1"}, {"pos": [960, -600], "type": "block-Snow-1"}, {"pos": [900, -600], "type": "block-Snow-1"}, {"pos": [840, -600], "type": "block-Snow-1"}, {"pos": [780, -600], "type": "block-Snow-1"}, {"pos": [720, -600], "type": "block-Snow-1"}, {"pos": [660, -600], "type": "block-Snow-1"}, {"pos": [600, -600], "type": "block-Snow-1"}, {"pos": [540, -600], "type": "block-Snow-1"}, {"pos": [480, -600], "type": "block-Snow-1"}, {"pos": [420, -600], "type": "block-Snow-1"}, {"pos": [240, -600], "type": "block-Snow-1"}, {"pos": [300, -600], "type": "block-Snow-1"}, {"pos": [360, -600], "type": "block-Snow-1"}, {"pos": [180, -600], "type": "block-Snow-1"}, {"pos": [120, -600], "type": "block-Snow-1"}, {"pos": [60, -600], "type": "block-Snow-1"}, {"pos": [0, -600], "type": "block-Snow-1"}, {"pos": [-60, -600], "type": "block-Snow-1"}, {"pos": [-120, -600], "type": "block-Snow-1"}, {"pos": [-840, -600], "type": "block-Snow-3"}, {"pos": [-480, -600], "type": "block-Snow-0"}, {"pos": [-420, -600], "type": "block-Snow-1"}, {"pos": [-360, -600], "type": "block-Snow-1"}, {"pos": [-300, -600], "type": "block-Snow-1"}, {"pos": [-240, -600], "type": "block-Snow-1"}, {"pos": [-180, -600], "type": "block-Snow-1"}, {"pos": [-840, -900], "type": "block-Snow-3"}, {"pos": [-840, -840], "type": "block-Snow-3"}, {"pos": [-840, -780], "type": "block-Snow-3"}, {"pos": [-840, -720], "type": "block-Snow-3"}, {"pos": [-840, -660], "type": "block-Snow-3"}, {"pos": [-840, -540], "type": "block-Snow-3"}, {"pos": [-840, -480], "type": "block-Snow-3"}, {"pos": [-840, -420], "type": "block-Snow-3"}, {"pos": [-840, -360], "type": "block-Snow-3"}, {"pos": [-840, -300], "type": "block-Snow-3"}, {"pos": [-660, -420], "type": "block-Snow-1"}, {"pos": [-840, -240], "type": "block-Snow-3"}, {"pos": [-780, -240], "type": "block-Snow-1"}, {"pos": [-720, -240], "type": "block-Snow-1"}, {"pos": [-660, -240], "type": "block-Snow-1"}, {"pos": [-600, -240], "type": "block-Snow-1"}, {"pos": [-540, -240], "type": "block-Snow-1"}, {"pos": [-480, -240], "type": "block-Snow-1"}, {"pos": [-420, -240], "type": "block-Snow-1"}, {"pos": [-360, -240], "type": "block-Snow-1"}, {"pos": [-300, -240], "type": "block-Snow-1"}, {"pos": [-240, -240], "type": "block-Snow-1"}, {"pos": [-180, -240], "type": "block-Snow-1"}, {"pos": [-120, -240], "type": "block-Snow-1"}, {"pos": [-60, -240], "type": "block-Snow-1"}, {"pos": [0, -240], "type": "block-Snow-1"}, {"pos": [60, -240], "type": "block-Snow-1"}, {"pos": [120, -240], "type": "block-Snow-1"}, {"pos": [180, -240], "type": "block-Snow-1"}, {"pos": [240, -240], "type": "block-Snow-1"}, {"pos": [300, -240], "type": "block-Snow-1"}, {"pos": [360, -240], "type": "block-Snow-1"}, {"pos": [420, -240], "type": "block-Snow-1"}, {"pos": [480, -240], "type": "block-Snow-1"}, {"pos": [540, -240], "type": "block-Snow-1"}, {"pos": [600, -240], "type": "block-Snow-1"}, {"pos": [660, -240], "type": "block-Snow-1"}, {"pos": [720, -240], "type": "block-Snow-1"}, {"pos": [780, -240], "type": "block-Snow-1"}, {"pos": [840, -240], "type": "block-Snow-1"}, {"pos": [900, -240], "type": "block-Snow-1"}, {"pos": [960, -240], "type": "block-Snow-1"}, {"pos": [1380, -540], "type": "block-Snow-3"}, {"pos": [1380, -480], "type": "block-Snow-3"}, {"pos": [1380, -420], "type": "block-Snow-3"}, {"pos": [1380, -360], "type": "block-Snow-3"}, {"pos": [1380, -300], "type": "block-Snow-3"}, {"pos": [1380, -240], "type": "block-Snow-3"}, {"pos": [1380, -180], "type": "block-Snow-3"}, {"pos": [1380, -120], "type": "block-Snow-3"}, {"pos": [1380, 0], "type": "block-Snow-3"}, {"pos": [1380, 60], "type": "block-Snow-3"}, {"pos": [1380, -60], "type": "block-Snow-3"}, {"pos": [1020, -240], "type": "block-Snow-2"}, {"pos": [1200, -60], "type": "block-Snow-1"}, {"pos": [1380, 120], "type": "block-Snow-3"}, {"pos": [1380, 180], "type": "block-Snow-3"}, {"pos": [1380, 240], "type": "block-Snow-3"}, {"pos": [1380, 300], "type": "block-Snow-3"}, {"pos": [1380, 360], "type": "block-Snow-3"}, {"pos": [1200, 300], "type": "block-Snow-1"}, {"pos": [1320, 120], "type": "block-Snow-0"}, {"pos": [1080, 120], "type": "block-Snow-1"}, {"pos": [1380, 420], "type": "block-Snow-3"}, {"pos": [1380, 480], "type": "block-Snow-3"}, {"pos": [1320, 480], "type": "block-Snow-1"}, {"pos": [1260, 480], "type": "block-Snow-1"}, {"pos": [1200, 480], "type": "block-Snow-1"}, {"pos": [1140, 480], "type": "block-Snow-1"}, {"pos": [1080, 480], "type": "block-Snow-1"}, {"pos": [1020, 480], "type": "block-Snow-1"}, {"pos": [960, 480], "type": "block-Snow-1"}, {"pos": [900, 480], "type": "block-Snow-1"}, {"pos": [840, 480], "type": "block-Snow-1"}, {"pos": [780, 480], "type": "block-Snow-1"}, {"pos": [720, 480], "type": "block-Snow-1"}, {"pos": [660, 480], "type": "block-Snow-1"}, {"pos": [600, 480], "type": "block-Snow-1"}, {"pos": [540, 480], "type": "block-Snow-1"}, {"pos": [480, 480], "type": "block-Snow-1"}, {"pos": [420, 480], "type": "block-Snow-1"}, {"pos": [360, 480], "type": "block-Snow-1"}, {"pos": [300, 480], "type": "block-Snow-1"}, {"pos": [240, 480], "type": "block-Snow-1"}, {"pos": [180, 480], "type": "block-Snow-1"}, {"pos": [120, 480], "type": "block-Snow-1"}, {"pos": [60, 480], "type": "block-Snow-1"}, {"pos": [0, 480], "type": "block-Snow-1"}, {"pos": [-60, 480], "type": "block-Snow-1"}, {"pos": [-120, 480], "type": "block-Snow-1"}, {"pos": [-180, 480], "type": "block-Snow-1"}, {"pos": [-240, 480], "type": "block-Snow-1"}, {"pos": [-300, 480], "type": "block-Snow-1"}, {"pos": [-360, 480], "type": "block-Snow-1"}, {"pos": [-420, 480], "type": "block-Snow-1"}, {"pos": [-480, 480], "type": "block-Snow-1"}, {"pos": [-540, 480], "type": "block-Snow-1"}, {"pos": [-600, 480], "type": "block-Snow-1"}, {"pos": [-660, 480], "type": "block-Snow-1"}, {"pos": [-720, 480], "type": "block-Snow-1"}, {"pos": [-780, 480], "type": "block-Snow-1"}, {"pos": [-840, 480], "type": "block-Snow-3"}, {"pos": [-840, 180], "type": "block-Snow-3"}, {"pos": [-840, 240], "type": "block-Snow-3"}, {"pos": [-840, 300], "type": "block-Snow-3"}, {"pos": [-840, 360], "type": "block-Snow-3"}, {"pos": [-840, 420], "type": "block-Snow-3"}, {"pos": [-840, 120], "type": "block-Snow-1"}, {"pos": [-420, -1020], "type": "enemy-buffalo"}, {"pos": [60, -1020], "type": "enemy-buffalo"}, {"pos": [-240, -1020], "type": "enemy-buffalo"}, {"pos": [360, -1020], "type": "enemy-buffalo"}, {"pos": [660, -1020], "type": "enemy-buffalo"}, {"pos": [540, -1020], "type": "enemy-buffalo"}, {"pos": [1200, -660], "type": "enemy-buffalo"}, {"pos": [780, -660], "type": "enemy-buffalo"}, {"pos": [1020, -660], "type": "enemy-buffalo"}, {"pos": [540, -660], "type": "enemy-buffalo"}, {"pos": [360, -660], "type": "enemy-buffalo"}, {"pos": [180, -660], "type": "enemy-buffalo"}, {"pos": [-120, -660], "type": "enemy-buffalo"}, {"pos": [-480, -300], "type": "enemy-buffalo"}, {"pos": [-120, -300], "type": "enemy-buffalo"}, {"pos": [-180, -300], "type": "enemy-buffalo"}, {"pos": [480, -300], "type": "enemy-buffalo"}, {"pos": [300, -300], "type": "enemy-buffalo"}, {"pos": [600, -300], "type": "enemy-buffalo"}, {"pos": [-177, 300], "type": "boss-buffalo"}, {"pos": [-720, 360], "type": "gates-1"}, {"pos": [-766, 420], "type": "traps-Fire"}, {"pos": [-585, 420], "type": "traps-Fire"}, {"pos": [15, 420], "type": "traps-Fire"}, {"pos": [496, 420], "type": "traps-Fire"}, {"pos": [733, 420], "type": "traps-Fire"}, {"pos": [251, 420], "type": "traps-Fire"}, {"pos": [-224, 420], "type": "traps-Fire"}, {"pos": [973, 420], "type": "traps-Fire"}, {"pos": [-287, -300], "type": "traps-Fire"}, {"pos": [191, -300], "type": "traps-Fire"}, {"pos": [733, -300], "type": "traps-Fire"}, {"pos": [-227, -660], "type": "traps-Fire"}, {"pos": [316, -660], "type": "traps-Fire"}, {"pos": [734, -660], "type": "traps-Fire"}, {"pos": [1092, -660], "type": "traps-Fire"}, {"pos": [-720, -1020], "type": "character-0"}, {"pos": [-420, -1200], "type": "tree-23"}, {"pos": [180, -1200], "type": "tree-23"}, {"pos": [780, -1200], "type": "tree-23"}, {"pos": [540, -840], "type": "tree-23"}, {"pos": [0, -840], "type": "tree-23"}, {"pos": [-409, -840], "type": "tree-23"}, {"pos": [-120, -840], "type": "tree-23"}, {"pos": [-540, -840], "type": "tree-23"}, {"pos": [-480, -480], "type": "tree-23"}, {"pos": [16, -480], "type": "tree-23"}, {"pos": [-158, -480], "type": "tree-23"}, {"pos": [300, -480], "type": "tree-23"}, {"pos": [734, -480], "type": "tree-23"}, {"pos": [913, -480], "type": "tree-23"}, {"pos": [660, -360], "type": "plant120x240-3"}, {"pos": [241, -360], "type": "plant120x240-3"}, {"pos": [-240, -360], "type": "plant120x240-3"}, {"pos": [-180, -720], "type": "plant120x240-3"}, {"pos": [900, -720], "type": "plant120x240-3"}, {"pos": [-120, -1080], "type": "plant120x240-3"}, {"pos": [120, -1080], "type": "plant120x240-3"}, {"pos": [480, -1080], "type": "plant120x240-3"}, {"pos": [720, -1080], "type": "plant120x240-3"}, {"pos": [600, -1080], "type": "plant120x240-13"}, {"pos": [0, -1080], "type": "plant120x240-13"}, {"pos": [-540, -1080], "type": "plant120x240-13"}, {"pos": [240, -720], "type": "plant120x240-13"}, {"pos": [960, -720], "type": "plant120x240-13"}, {"pos": [540, -360], "type": "plant120x240-13"}, {"pos": [-540, -360], "type": "plant120x240-13"}, {"pos": [-600, -300], "type": "enemy-thorn"}, {"pos": [0, -300], "type": "enemy-thorn"}, {"pos": [60, -300], "type": "enemy-thorn"}, {"pos": [420, -660], "type": "enemy-thorn"}, {"pos": [480, -660], "type": "plant120x120-16"}, {"pos": [840, -660], "type": "enemy-thorn"}, {"pos": [-180, -1020], "type": "enemy-thorn"}, {"pos": [-60, -1020], "type": "enemy-thorn"}, {"pos": [180, -1020], "type": "enemy-thorn"}, {"pos": [420, -1020], "type": "enemy-thorn"}]